README.md
setup.cfg
setup.py
pyva/__init__.py
pyva/closureValidationRule.py
pyva/helpers.py
pyva/validationException.py
pyva/validator.py
pyva.egg-info/PKG-INFO
pyva.egg-info/SOURCES.txt
pyva.egg-info/dependency_links.txt
pyva.egg-info/requires.txt
pyva.egg-info/top_level.txt
pyva/Rules/__init__.py
pyva/Rules/ruleContract.py
pyva/tests/TestDependentRules.py
pyva/tests/TestEmailRule.py
pyva/tests/TestIpRules.py
pyva/tests/TestNumericRules.py
pyva/tests/TestRules.py
pyva/tests/TestSizeRules.py
pyva/tests/TestUrlRule.py
pyva/tests/__init__.py