Metadata-Version: 2.1
Name: pyva
Version: 0.4.1
Summary: Simple and flexible python data validation library
Home-page: https://github.com/holoyan/python-data-validation
Author: Artak
Author-email: artaksafaryanc@gmail.com
License: MIT
Keywords: data,validation,validator,data validator
Platform: UNKNOWN
Classifier: Development Status :: 3 - Alpha
Classifier: Intended Audience :: Developers
Classifier: Topic :: Software Development :: Build Tools
Classifier: License :: OSI Approved :: MIT License
Classifier: Programming Language :: Python :: 3
Classifier: Programming Language :: Python :: 3.5
Classifier: Programming Language :: Python :: 3.6
Classifier: Programming Language :: Python :: 3.7
Classifier: Programming Language :: Python :: 3.8
